Metadata-Version: 2.1
Name: perfil
Version: 0.1.4
Summary: Profile Python functions.
Home-page: https://github.com/JCPedroza/perfil
Author: JCPedroza
Author-email: <nemesis4go10@hotmail.com>
License: MIT
Platform: UNKNOWN
Classifier: Programming Language :: Python :: 3.10
License-File: LICENSE
